{
  "type" :         "matt.mstruct.bj.BasicJvmOnlyMod",
  "jvmExec" :      {
	"type" : "Typical"
  },
  "dependencies" : [

	{
	  "type" : "matt.mstruct.bj.BuildJsonProjectDependency",
	  "cfg" :  "implementation",
	  "path" : ":k:fx:node:tex"
	},
	{
	  "type" : "matt.mstruct.bj.BuildJsonProjectDependency",
	  "cfg" :  "implementation",
	  "path" : ":k:fx:node:proto"
	},
	{
	  "type" : "matt.mstruct.bj.BuildJsonLibDependency",
	  "cfg" :  "implementation",
	  "key" :  "slf4j-nop"
	},
	{
	  "type" : "matt.mstruct.bj.BuildJsonProjectDependency",
	  "cfg" :  "implementation",
	  "path" : ":k:math:mat"
	},
	{
	  "type" : "matt.mstruct.bj.BuildJsonProjectDependency",
	  "cfg" :  "implementation",
	  "path" : ":k:kjlib:git"
	},
	{
	  "type" : "matt.mstruct.bj.BuildJsonProjectDependency",
	  "cfg" :  "testImplementation",
	  "path" : ":k:test"
	},
	{
	  "type" : "matt.mstruct.bj.BuildJsonProjectDependency",
	  "cfg" :  "testImplementation",
	  "path" : ":k:gui"
	},
	{
	  "type" : "matt.mstruct.bj.BuildJsonProjectDependency",
	  "cfg" :  "testImplementation",
	  "path" : ":k:log:profile:yk"
	},
	{
	  "type" : "matt.mstruct.bj.BuildJsonLibDependency",
	  "cfg" :  "implementation",
	  "key" :  "guava"
	}
  ]
}